texatlas
texatlas-stubs
